[
      {
        "id": 1,
        "product": "Product A",
        "quantity": 5,
        "due": false,
        "rate": 25.99
      },
      {
        "id": 2,
        "product": "Product B",
        "quantity": 10,
        "due": false,
        "rate": 12.50
      },
      {
        "id": 3,
        "product": "Prodwefewfdsfdsf sdfsd fds dffghfgh fgh ydhjuct C",
        "quantity": 2,
        "due": false,
        "rate": 233345345345.75
      },
      {
        "id": 4,
        "product": "Product D",
        "quantity": 8,
        "due": false,
        "rate": 19.99
      },
      {
        "id": 5,
        "product": "Product E",
        "quantity": 15,
        "due": false,
        "rate": 8.95
      },
      {
        "id": 6,
        "product": "Product F",
        "quantity": 3,
        "due": false,
        "rate": 33.25
      },
      {
        "id": 7,
        "product": "Product G",
        "quantity": 7,
        "due": false,
        "rate": 14.75
      },
      {
        "id": 8,
        "product": "Product H",
        "quantity": 12,
        "due": false,
        "rate": 9.99
      },
      {
        "id": 9,
        "product": "Product I",
        "quantity": 4,
        "due": false,
        "rate": 28.50
      },
      {
        "id": 10,
        "product": "Product J",
        "quantity": 6,
        "due": false,
        "rate": 17.95
      }
    ]

  